biliass-2.3.1.dist-info/METADATA
biliass-2.3.1.dist-info/WHEEL
biliass-2.3.1.dist-info/entry_points.txt
biliass-2.3.1.dist-info/licenses/LICENSE
biliass/__init__.py
biliass/__main__.py
biliass/__version__.py
biliass/_core.abi3.so
biliass/_core.pyi
biliass/biliass.py
biliass/py.typed
biliass-2.3.1.dist-info/RECORD
