Metadata-Version: 2.4
Name: biliass
Version: 2.3.1
Classifier: Operating System :: OS Independent
Classifier: License :: OSI Approved :: GNU General Public License v3 (GPLv3)
Classifier: Programming Language :: Rust
Classifier: Programming Language :: Python
Classifier: Programming Language :: Python :: 3
Classifier: Programming Language :: Python :: 3.10
Classifier: Programming Language :: Python :: 3.11
Classifier: Programming Language :: Python :: 3.12
Classifier: Programming Language :: Python :: 3.13
Classifier: Programming Language :: Python :: 3.14
Classifier: Programming Language :: Python :: Implementation :: CPython
Classifier: Programming Language :: Python :: Free Threading :: 4 - Resilient
License-File: LICENSE
Summary: 💬 将 B 站 XML/protobuf 弹幕转换为 ASS 弹幕
Keywords: bilibili,yutto,danmaku,ASS
Author-email: Star Brilliant <m13253@hotmail.com>, Nyakku Shigure <sigure.qaq@gmail.com>
Requires-Python: >=3.10
Project-URL: Homepage, https://github.com/yutto-dev/yutto/tree/main/packages/biliass
Project-URL: Documentation, https://github.com/yutto-dev/yutto/tree/main/packages/biliass
Project-URL: Repository, https://github.com/yutto-dev/yutto
Project-URL: Issues, https://github.com/yutto-dev/yutto/issues
